[{
		"Name": "Ecole Nationale de Commerce et de Gestion Agadir (ENCGA1)"
	},
	{
		"Name": "Ecole Nationale des Sciences Appliquées Agadir (ENSA)"

	},
	{
		"Name": "Faculté des Lettres et des Sciences Humaines Agadir (FLSH)"

	},
	{
		"Name": "Faculté Polydisciplinaire Ouarzazate (FPO))"

	},
	{
		"Name": "Faculté Polydisciplinaire Taroudant (FPT)"

	},
	{
		"Name": "Faculté des Sciences Agadir (FSA)"

	},
	{
		"Name": "Faculté des Sciences Juridiques, Economiques et Sociales Agadir (FSJESA)"

	},
	{
		"Name": "Présidence de l'Université Ibn Zohr (PUIZ)"

	}





]
